gitrconfig.py
git_r-0.1.4.data/scripts/git-r
git_r-0.1.4.dist-info/DESCRIPTION.rst
git_r-0.1.4.dist-info/METADATA
git_r-0.1.4.dist-info/RECORD
git_r-0.1.4.dist-info/WHEEL
git_r-0.1.4.dist-info/metadata.json
git_r-0.1.4.dist-info/top_level.txt
