Metadata-Version: 2.0
Name: git-r
Version: 0.1.4
Summary: Manage git repo from a distant location (within the same machine)
Home-page: https://github.com/JulienPeloton/git-r
Author: Julien Peloton
Author-email: j.peloton@sussex.ac.uk
License: GPL-3.0
Download-URL: https://github.com/JulienPeloton/git-r/archive/0.1.4.tar.gz
Platform: any
Classifier: Development Status :: 3 - Alpha
Classifier: Environment :: Console
Classifier: Intended Audience :: Developers
Classifier: License :: OSI Approved :: GNU General Public License v3 (GPLv3)
Classifier: Operating System :: OS Independent
Classifier: Programming Language :: Python
Classifier: Programming Language :: Python :: 2
Classifier: Programming Language :: Python :: 3
Classifier: Topic :: Software Development :: Version Control
